AMANDA047/__init__.py
AMANDA047/classes_and_methods.py
AMANDA047-0.0.3.dist-info/LICENSE.txt
AMANDA047-0.0.3.dist-info/METADATA
AMANDA047-0.0.3.dist-info/WHEEL
AMANDA047-0.0.3.dist-info/top_level.txt
AMANDA047-0.0.3.dist-info/RECORD
